configoat/__init__.py
configoat/cli.py
configoat/configoat.py
configoat/templates/config.yaml
configoat/templates/main.yaml
configoat/templates/main_nested.yaml
configoat/templates/main_nested_script.yaml
configoat/templates/nested.yaml
configoat/templates/script.py
configoat-0.1.6.dist-info/AUTHORS.rst
configoat-0.1.6.dist-info/LICENSE
configoat-0.1.6.dist-info/METADATA
configoat-0.1.6.dist-info/WHEEL
configoat-0.1.6.dist-info/entry_points.txt
configoat-0.1.6.dist-info/top_level.txt
configoat-0.1.6.dist-info/RECORD
