Metadata-Version: 2.1
Name: configoat
Version: 0.1.6
Summary: confiGOAT is a powerful, flexible, and developer-friendly configuration management tool.
Home-page: https://github.com/aag13/configoat
Author: Hasan-UL-Banna, Asadullah Al Galib
Author-email: hasanulbanna04056@gmail.com, asadullahgalib13@gmail.com
License: MIT license
Keywords: configoat
Platform: UNKNOWN
Classifier: Development Status :: 4 - Beta
Classifier: Framework :: Django
Classifier: Framework :: Flask
Classifier: Intended Audience :: Developers
Classifier: License :: OSI Approved :: MIT License
Classifier: Natural Language :: English
Classifier: Operating System :: OS Independent
Classifier: Programming Language :: Python :: 3
Classifier: Programming Language :: Python :: 3.5
Classifier: Programming Language :: Python :: 3.6
Classifier: Programming Language :: Python :: 3.7
Classifier: Programming Language :: Python :: 3.8
Classifier: Topic :: Software Development :: Libraries
Requires-Python: >=3.5
Requires-Dist: Click >=7.0
Requires-Dist: PyYAML >=5.0
